Hanita-0.1.3.dist-info/DESCRIPTION.rst
Hanita-0.1.3.dist-info/METADATA
Hanita-0.1.3.dist-info/RECORD
Hanita-0.1.3.dist-info/WHEEL
Hanita-0.1.3.dist-info/metadata.json
Hanita-0.1.3.dist-info/top_level.txt
hanita/__init__.py
hanita/__main__.py
hanita/client.py
hanita/client_connection.py
hanita/client_db.py
hanita/client_qtview.py
hanita/forms/__init__.py
hanita/forms/app_ui.py
hanita/forms/form_contacts.py
hanita/forms/form_login.py
hanita/forms/form_main.py
hanita/forms/form_new_chat.py
hanita/forms/just_ui.py
hanita/forms/templates/default_avatar.png
hanita/forms/templates/schema.py
hanita/forms/templates/template.html
hanita_JIM/__init__.py
hanita_JIM/jimmessage.py
hanita_server/__init__.py
hanita_server/__main__.py
hanita_server/models.py
hanita_server/request_handler.py
hanita_server/server.py
hanita_server/server_db.py
hanita_server/avatars/default_avatar.png
