Metadata-Version: 2.0
Name: Hanita
Version: 0.1.3
Summary: Simple messenger.
Home-page: https://github.com/machine23/hanita
Author: Vassili Baranov
Author-email: vassili.baranov@gmail.com
License: MIT
Keywords: python,messenger,hanita
Platform: UNKNOWN
Requires-Python: >=3.5
Requires-Dist: PyQt5 (==5.9)
Requires-Dist: SQLAlchemy (==1.1.15)
Requires-Dist: Jinja2 (==2.10)
Requires-Dist: Pillow (==5.0.0)
Requires-Dist: PyOpenGL (==3.1.0)
Requires-Dist: pymongo (==3.6.0)
